agentaction/__init__.py
agentaction/main.py
agentaction-0.1.7.dist-info/LICENSE
agentaction-0.1.7.dist-info/METADATA
agentaction-0.1.7.dist-info/WHEEL
agentaction-0.1.7.dist-info/top_level.txt
agentaction-0.1.7.dist-info/RECORD
